baqup_schema/__init__.py
baqup_schema/py.typed
baqup_schema-0.0.1.dist-info/METADATA
baqup_schema-0.0.1.dist-info/WHEEL
baqup_schema-0.0.1.dist-info/licenses/LICENSE
baqup_schema-0.0.1.dist-info/RECORD
