Metadata-Version: 2.4
Name: baqup-schema
Version: 0.0.1
Summary: JSON Schema validation and environment variable loading for baqup agent configuration
Project-URL: Homepage, https://github.com/baqupio/baqup
Project-URL: Documentation, https://github.com/baqupio/baqup/blob/main/AGENT-CONTRACT-SPEC.md
Project-URL: Repository, https://github.com/baqupio/baqup-schema-py
Project-URL: Issues, https://github.com/baqupio/baqup/issues
Author-email: baqupio <hello@baqup.io>
License: Fair Source License, Version 1.0
License-File: LICENSE
Keywords: backup,baqup,container,docker,json-schema,schema,validation
Classifier: Development Status :: 1 - Planning
Classifier: Intended Audience :: Developers
Classifier: Intended Audience :: System Administrators
Classifier: Operating System :: OS Independent
Classifier: Programming Language :: Python :: 3
Classifier: Programming Language :: Python :: 3.10
Classifier: Programming Language :: Python :: 3.11
Classifier: Programming Language :: Python :: 3.12
Classifier: Topic :: System :: Archiving :: Backup
Classifier: Topic :: System :: Systems Administration
Requires-Python: >=3.10
Requires-Dist: jsonschema>=4.0.0
